cloudcms/__init__.py
cloudcms/cloudcms.py
cloudcms/association/__init__.py
cloudcms/association/association.py
cloudcms/association/direction.py
cloudcms/association/directionality.py
cloudcms/attachment/__init__.py
cloudcms/attachment/attachment.py
cloudcms/branch/__init__.py
cloudcms/branch/branch.py
cloudcms/error/__init__.py
cloudcms/error/invalid_qname_error.py
cloudcms/error/job_error.py
cloudcms/error/request_error.py
cloudcms/job/__init__.py
cloudcms/job/job.py
cloudcms/node/__init__.py
cloudcms/node/base_node.py
cloudcms/node/node.py
cloudcms/node/traversal_results.py
cloudcms/platform/__init__.py
cloudcms/platform/cloudcms_object.py
cloudcms/platform/platform.py
cloudcms/project/__init__.py
cloudcms/project/project.py
cloudcms/release/__init__.py
cloudcms/release/release.py
cloudcms/repository/__init__.py
cloudcms/repository/repository.py
cloudcms/repository/repository_object.py
cloudcms/support/__init__.py
cloudcms/support/connection_config.py
cloudcms/support/qname.py
tests/__init__.py
tests/abstract_test.py
tests/abstract_with_repository_test.py
tests/test_association.py
tests/test_attachment.py
tests/test_branch.py
tests/test_deployment_target.py
tests/test_file_folder.py
tests/test_graphql.py
tests/test_node.py
tests/test_platform.py
tests/test_project.py
tests/test_release.py
tests/test_repository.py
tests/test_traverse.py
cloudcms-1.1.4.dist-info/LICENSE
cloudcms-1.1.4.dist-info/METADATA
cloudcms-1.1.4.dist-info/WHEEL
cloudcms-1.1.4.dist-info/top_level.txt
cloudcms-1.1.4.dist-info/RECORD
