Metadata-Version: 2.1
Name: cloudcms
Version: 1.1.4
Summary: Cloud CMS Python Driver
Home-page: https://github.com/gitana/cloudcms-python-driver
Author: Michael Whitman
Author-email: michael.whitman@cloudcms.com
Classifier: Programming Language :: Python
Classifier: License :: OSI Approved :: Apache Software License
Classifier: Operating System :: OS Independent
License-File: LICENSE
Requires-Dist: oauthlib (>=3.0.0)
Requires-Dist: requests (>=2.0.0)
Requires-Dist: requests-oauthlib (>=1.0.0)
